{
  "additional_notices": [],
  "asset_platform_id": "ethereum",
  "block_time_in_minutes": 0,
  "categories": [
    "Meme",
    "Ethereum Ecosystem",
    "The Boy\u2019s Club"
  ],
  "community_data": {
    "facebook_likes": null,
    "reddit_accounts_active_48h": 0,
    "reddit_average_comments_48h": 0,
    "reddit_average_posts_48h": 0,
    "reddit_subscribers": 0,
    "telegram_channel_user_count": 2998,
    "twitter_followers": 12152
  },
  "contract_address": "0xbe042e9d09cb588331ff911c2b46fd833a3e5bd6",
  "country_origin": "",
  "description": {
    "ar": "",
    "bg": "",
    "cs": "",
    "da": "",
    "de": "",
    "el": "",
    "en": "The project is about the most famous meme \"Pepe the Frog\". \r\nIts unique because it's fully decentralized meaning the deployer doesn't hold any supply, the Liquidity is 100% burned and the contract is fully renounced.\r\nThe Project is around one day old, built with the mission to spread true decentralization of meme coins in the crypto space.\r\nThis is a meme coin, so it does not have a utility, but built on the togetherness of a community.\r\n\r\nAccording to the true philosophy of DeFi and meme coins, it is traded on the open market, where everyone is treated the same way. Everyone can buy and sell however they'd like, with no restrictions.\r\n$Pepe has ABSOLUTELY NO blacklisting of ANY buyer.\r\n$Pepe NO taxes.\r\nThere is NO centralized owner of the $PEPE contract.\r\nThe liquidity pair of $Pepe is BURNT (Sent to 0xdead), ensuring no one can ever hurt the community by removing it.\r\n\r\nThis is the true $Pepe, which encourages community, memetic warfare against normies and financial freedom following the philosophy of DeFi.",
    "es": "",
    "fi": "",
    "fr": "",
    "he": "",
    "hi": "",
    "hr": "",
    "hu": "",
    "id": "",
    "it": "",
    "ja": "",
    "ko": "",
    "lt": "",
    "nl": "",
    "no": "",
    "pl": "",
    "pt": "",
    "ro": "",
    "ru": "",
    "sk": "",
    "sl": "",
    "sv": "",
    "th": "",
    "tr": "",
    "uk": "",
    "vi": "",
    "zh": "",
    "zh-tw": ""
  },
  "detail_platforms": {
    "ethereum": {
      "contract_address": "0xbe042e9d09cb588331ff911c2b46fd833a3e5bd6",
      "decimal_place": 18
    }
  },
  "developer_data": {
    "closed_issues": 0,
    "code_additions_deletions_4_weeks": {
      "additions": null,
      "deletions": null
    },
    "commit_count_4_weeks": 0,
    "forks": 0,
    "last_4_weeks_commit_activity_series": [],
    "pull_request_contributors": 0,
    "pull_requests_merged": 0,
    "stars": 0,
    "subscribers": 0,
    "total_issues": 0
  },
  "genesis_date": null,
  "hashing_algorithm": null,
  "id": "pepe-token",
  "image": {
    "large": "https://coin-images.coingecko.com/coins/images/31482/large/photo_2023-08-25_07-54-16.jpg?1696530294",
    "small": "https://coin-images.coingecko.com/coins/images/31482/small/photo_2023-08-25_07-54-16.jpg?1696530294",
    "thumb": "https://coin-images.coingecko.com/coins/images/31482/thumb/photo_2023-08-25_07-54-16.jpg?1696530294"
  },
  "last_updated": "2024-12-17T12:19:35.474Z",
  "links": {
    "announcement_url": [
      "",
      ""
    ],
    "bitcointalk_thread_identifier": null,
    "blockchain_site": [
      "https://etherscan.io/token/0xbe042e9d09cb588331ff911c2b46fd833a3e5bd6",
      "https://platform.arkhamintelligence.com/explorer/token/pepe-token",
      "https://ethplorer.io/address/0xbe042e9d09cb588331ff911c2b46fd833a3e5bd6",
      null,
      null,
      "",
      "",
      "",
      "",
      ""
    ],
    "chat_url": [
      "",
      "",
      ""
    ],
    "facebook_username": "",
    "homepage": [
      "https://pepecommunity.vip",
      "",
      ""
    ],
    "official_forum_url": [
      "https://www.lbank.com/en-US/trade/pepenew_usdt/",
      "",
      ""
    ],
    "repos_url": {
      "bitbucket": [],
      "github": []
    },
    "snapshot_url": null,
    "subreddit_url": "https://www.reddit.com",
    "telegram_channel_identifier": "PepeCommunityEntry",
    "twitter_screen_name": "PepeCommunity_",
    "whitepaper": ""
  },
  "localization": {
    "ar": "",
    "bg": "",
    "cs": "",
    "da": "",
    "de": "",
    "el": "",
    "en": "Pepe Token",
    "es": "",
    "fi": "",
    "fr": "",
    "he": "",
    "hi": "",
    "hr": "",
    "hu": "",
    "id": "",
    "it": "",
    "ja": "",
    "ko": "",
    "lt": "",
    "nl": "",
    "no": "",
    "pl": "",
    "pt": "",
    "ro": "",
    "ru": "",
    "sk": "",
    "sl": "",
    "sv": "",
    "th": "",
    "tr": "",
    "uk": "",
    "vi": "",
    "zh": "",
    "zh-tw": ""
  },
  "market_cap_rank": 5005,
  "market_data": {
    "ath": {
      "aed": 0.108988,
      "ars": 10.38,
      "aud": 0.04606481,
      "bch": 0.00015511,
      "bdt": 3.24,
      "bhd": 0.01118668,
      "bits": 1.14,
      "bmd": 0.02967233,
      "bnb": 0.00013599,
      "brl": 0.144626,
      "btc": 1.14e-06,
      "cad": 0.04034472,
      "chf": 0.02619533,
      "clp": 25.22,
      "cny": 0.216255,
      "czk": 0.661758,
      "dkk": 0.204114,
      "dot": 0.00638012,
      "eos": 0.0502237,
      "eth": 1.795e-05,
      "eur": 0.0273872,
      "gbp": 0.02350081,
      "gel": 0.010426,
      "hkd": 0.232817,
      "huf": 10.5,
      "idr": 453.15,
      "ils": 0.112861,
      "inr": 2.45,
      "jpy": 4.34,
      "krw": 39.21,
      "kwd": 0.00915095,
      "link": 0.00497661,
      "lkr": 9.59,
      "ltc": 0.00045358,
      "mmk": 62.32,
      "mxn": 0.497914,
      "myr": 0.137991,
      "ngn": 22.86,
      "nok": 0.317317,
      "nzd": 0.050145,
      "php": 1.68,
      "pkr": 9,
      "pln": 0.122362,
      "rub": 2.84,
      "sar": 0.111317,
      "sats": 113.78,
      "sek": 0.32495,
      "sgd": 0.04018271,
      "thb": 1.045,
      "try": 0.78305,
      "twd": 0.946087,
      "uah": 1.096,
      "usd": 0.02967233,
      "vef": 0.00297109,
      "vnd": 714.65,
      "xag": 0.00122547,
      "xau": 1.544e-05,
      "xdr": 0.02233902,
      "xlm": 0.24819667,
      "xrp": 0.05699332,
      "yfi": 5.23e-06,
      "zar": 0.550737
    },
    "ath_change_percentage": {
      "aed": -98.43632,
      "ars": -95.43706,
      "aud": -98.41246,
      "bch": -99.4468,
      "bdt": -98.29482,
      "bhd": -98.43594,
      "bits": -99.61812,
      "bmd": -98.43629,
      "bnb": -99.5259,
      "brl": -98.03183,
      "btc": -99.61812,
      "cad": -98.35784,
      "chf": -98.41141,
      "clp": -98.18711,
      "cny": -98.43706,
      "czk": -98.32512,
      "dkk": -98.38397,
      "dot": -99.18394,
      "eos": -99.14532,
      "eth": -99.35313,
      "eur": -98.38538,
      "gbp": -98.44544,
      "gel": -87.50578,
      "hkd": -98.45168,
      "huf": -98.27438,
      "idr": -98.34692,
      "ils": -98.5171,
      "inr": -98.3929,
      "jpy": -98.35609,
      "krw": -98.29812,
      "kwd": -98.44028,
      "link": -99.67161,
      "lkr": -98.598,
      "ltc": -99.14074,
      "mmk": -98.43796,
      "mxn": -98.12614,
      "myr": -98.49816,
      "ngn": -96.85692,
      "nok": -98.36081,
      "nzd": -98.39373,
      "php": -98.37196,
      "pkr": -98.56977,
      "pln": -98.45914,
      "rub": -98.32171,
      "sar": -98.43396,
      "sats": -99.61812,
      "sek": -98.43979,
      "sgd": -98.44049,
      "thb": -98.48048,
      "try": -97.92668,
      "twd": -98.40525,
      "uah": -98.23657,
      "usd": -98.43629,
      "vef": -98.43629,
      "vnd": -98.3488,
      "xag": -98.75127,
      "xau": -98.86275,
      "xdr": -98.42032,
      "xlm": -99.59694,
      "xrp": -99.69844,
      "yfi": -99.16275,
      "zar": -98.4778
    },
    "ath_date": {
      "aed": "2023-08-29T02:14:47.645Z",
      "ars": "2023-08-29T02:14:47.645Z",
      "aud": "2023-08-29T02:14:47.645Z",
      "bch": "2023-08-29T02:14:47.645Z",
      "bdt": "2023-08-29T02:14:47.645Z",
      "bhd": "2023-08-29T02:14:47.645Z",
      "bits": "2023-08-29T02:14:47.645Z",
      "bmd": "2023-08-29T02:14:47.645Z",
      "bnb": "2023-08-29T02:14:47.645Z",
      "brl": "2023-08-29T02:14:47.645Z",
      "btc": "2023-08-29T02:14:47.645Z",
      "cad": "2023-08-29T02:14:47.645Z",
      "chf": "2023-08-29T02:14:47.645Z",
      "clp": "2023-08-29T02:14:47.645Z",
      "cny": "2023-08-29T02:14:47.645Z",
      "czk": "2023-08-29T02:14:47.645Z",
      "dkk": "2023-08-29T02:14:47.645Z",
      "dot": "2023-08-29T02:14:47.645Z",
      "eos": "2023-08-29T02:20:22.328Z",
      "eth": "2023-08-29T02:14:47.645Z",
      "eur": "2023-08-29T02:14:47.645Z",
      "gbp": "2023-08-29T02:14:47.645Z",
      "gel": "2024-03-08T12:20:21.122Z",
      "hkd": "2023-08-29T02:14:47.645Z",
      "huf": "2023-08-29T02:14:47.645Z",
      "idr": "2023-08-29T02:14:47.645Z",
      "ils": "2023-08-29T02:14:47.645Z",
      "inr": "2023-08-29T02:14:47.645Z",
      "jpy": "2023-08-29T02:14:47.645Z",
      "krw": "2023-08-29T02:14:47.645Z",
      "kwd": "2023-08-29T02:14:47.645Z",
      "link": "2023-08-29T02:14:47.645Z",
      "lkr": "2023-08-29T02:14:47.645Z",
      "ltc": "2023-08-29T02:14:47.645Z",
      "mmk": "2023-08-29T02:14:47.645Z",
      "mxn": "2023-08-29T02:14:47.645Z",
      "myr": "2023-08-29T02:14:47.645Z",
      "ngn": "2023-08-29T02:14:47.645Z",
      "nok": "2023-08-29T02:14:47.645Z",
      "nzd": "2023-08-29T02:14:47.645Z",
      "php": "2023-08-29T02:14:47.645Z",
      "pkr": "2023-08-29T02:14:47.645Z",
      "pln": "2023-08-29T02:14:47.645Z",
      "rub": "2023-08-29T02:14:47.645Z",
      "sar": "2023-08-29T02:14:47.645Z",
      "sats": "2023-08-29T02:14:47.645Z",
      "sek": "2023-08-29T02:14:47.645Z",
      "sgd": "2023-08-29T02:14:47.645Z",
      "thb": "2023-08-29T02:14:47.645Z",
      "try": "2023-08-29T02:14:47.645Z",
      "twd": "2023-08-29T02:14:47.645Z",
      "uah": "2023-08-29T02:14:47.645Z",
      "usd": "2023-08-29T02:14:47.645Z",
      "vef": "2023-08-29T02:14:47.645Z",
      "vnd": "2023-08-29T02:14:47.645Z",
      "xag": "2023-08-29T02:14:47.645Z",
      "xau": "2023-08-29T02:14:47.645Z",
      "xdr": "2023-08-29T02:14:47.645Z",
      "xlm": "2023-08-29T02:14:47.645Z",
      "xrp": "2023-08-29T02:14:47.645Z",
      "yfi": "2023-08-29T02:14:47.645Z",
      "zar": "2023-08-29T02:14:47.645Z"
    },
    "atl": {
      "aed": 0.00149489,
      "ars": 0.3898,
      "aud": 0.00061037,
      "bch": 7.20063e-07,
      "bdt": 0.0486532,
      "bhd": 0.00015336,
      "bits": 0.00423545,
      "bmd": 0.000407,
      "bnb": 5.97484e-07,
      "brl": 0.00227357,
      "btc": 4.235e-09,
      "cad": 0.00055233,
      "chf": 0.00034499,
      "clp": 0.384034,
      "cny": 0.00289737,
      "czk": 0.0092428,
      "dkk": 0.00275205,
      "dot": 4.097e-05,
      "eos": 0.00031379,
      "eth": 1.12055e-07,
      "eur": 0.0003688,
      "gbp": 0.00031081,
      "gel": 0.00109686,
      "hkd": 0.00317323,
      "huf": 0.146453,
      "idr": 6.29,
      "ils": 0.00153385,
      "inr": 0.03417882,
      "jpy": 0.058259,
      "krw": 0.546111,
      "kwd": 0.00012434,
      "link": 1.497e-05,
      "lkr": 0.122306,
      "ltc": 3.18e-06,
      "mmk": 0.85388,
      "mxn": 0.00809958,
      "myr": 0.00174244,
      "ngn": 0.669624,
      "nok": 0.00438895,
      "nzd": 0.00066088,
      "php": 0.02294304,
      "pkr": 0.113452,
      "pln": 0.00157967,
      "rub": 0.03712881,
      "sar": 0.00152704,
      "sats": 0.423545,
      "sek": 0.00421629,
      "sgd": 0.00053112,
      "thb": 0.01374582,
      "try": 0.01385951,
      "twd": 0.01309187,
      "uah": 0.01676863,
      "usd": 0.000407,
      "vef": 4.075e-05,
      "vnd": 10.04,
      "xag": 1.291e-05,
      "xau": 1.5885e-07,
      "xdr": 0.00030177,
      "xlm": 0.00088032,
      "xrp": 0.00017122,
      "yfi": 3.4267e-08,
      "zar": 0.00728299
    },
    "atl_change_percentage": {
      "aed": 14.00327,
      "ars": 21.56147,
      "aud": 19.81113,
      "bch": 19.16407,
      "bdt": 13.62698,
      "bhd": 14.08647,
      "bits": 2.58433,
      "bmd": 14.00296,
      "bnb": 7.91008,
      "brl": 25.19877,
      "btc": 2.58433,
      "cad": 19.95136,
      "chf": 20.62232,
      "clp": 19.05443,
      "cny": 16.6549,
      "czk": 19.91686,
      "dkk": 19.85724,
      "dot": 27.09271,
      "eos": 36.79669,
      "eth": 3.6237,
      "eur": 19.90235,
      "gbp": 17.5417,
      "gel": 18.7619,
      "hkd": 13.59889,
      "huf": 23.73718,
      "idr": 19.11759,
      "ils": 9.11197,
      "inr": 15.26633,
      "jpy": 22.56484,
      "krw": 22.18469,
      "kwd": 14.79034,
      "link": 9.18911,
      "lkr": 9.97557,
      "ltc": 22.49558,
      "mmk": 14.00296,
      "mxn": 15.1934,
      "myr": 18.93689,
      "ngn": 7.31362,
      "nok": 18.51213,
      "nzd": 21.87864,
      "php": 19.30253,
      "pkr": 13.40221,
      "pln": 19.35527,
      "rub": 28.18335,
      "sar": 14.15957,
      "sats": 2.58433,
      "sek": 20.24537,
      "sgd": 17.98802,
      "thb": 15.55991,
      "try": 17.14086,
      "twd": 15.24477,
      "uah": 15.25356,
      "usd": 14.00296,
      "vef": 14.00296,
      "vnd": 17.52568,
      "xag": 18.52199,
      "xau": 10.51326,
      "xdr": 16.93706,
      "xlm": 13.6376,
      "xrp": 0.37619,
      "yfi": 27.86794,
      "zar": 15.10847
    },
    "atl_date": {
      "aed": "2024-09-10T11:21:15.444Z",
      "ars": "2024-09-10T11:21:15.444Z",
      "aud": "2024-09-10T11:21:15.444Z",
      "bch": "2024-12-05T07:03:15.394Z",
      "bdt": "2024-09-10T11:21:15.444Z",
      "bhd": "2024-09-10T11:21:15.444Z",
      "bits": "2024-12-05T07:03:15.394Z",
      "bmd": "2024-09-10T11:21:15.444Z",
      "bnb": "2024-12-05T07:03:15.394Z",
      "brl": "2024-09-10T11:21:15.444Z",
      "btc": "2024-12-05T07:03:15.394Z",
      "cad": "2024-09-10T11:21:15.444Z",
      "chf": "2024-09-10T11:21:15.444Z",
      "clp": "2024-09-10T11:21:15.444Z",
      "cny": "2024-09-10T11:21:15.444Z",
      "czk": "2024-09-10T11:21:15.444Z",
      "dkk": "2024-09-10T11:21:15.444Z",
      "dot": "2024-12-05T20:16:04.584Z",
      "eos": "2024-12-05T16:34:31.028Z",
      "eth": "2024-12-05T07:03:15.394Z",
      "eur": "2024-09-10T11:21:15.444Z",
      "gbp": "2024-09-10T11:21:15.444Z",
      "gel": "2024-09-10T11:21:15.444Z",
      "hkd": "2024-09-10T11:21:15.444Z",
      "huf": "2024-09-10T11:21:15.444Z",
      "idr": "2024-09-10T11:21:15.444Z",
      "ils": "2024-09-10T11:21:15.444Z",
      "inr": "2024-09-10T11:21:15.444Z",
      "jpy": "2024-09-10T11:21:15.444Z",
      "krw": "2024-09-10T11:21:15.444Z",
      "kwd": "2024-09-10T11:21:15.444Z",
      "link": "2024-12-16T15:46:28.307Z",
      "lkr": "2024-09-10T11:21:15.444Z",
      "ltc": "2024-12-05T19:55:33.600Z",
      "mmk": "2024-09-10T11:21:15.444Z",
      "mxn": "2024-09-10T11:21:15.444Z",
      "myr": "2024-09-25T01:06:18.301Z",
      "ngn": "2024-09-10T11:21:15.444Z",
      "nok": "2024-09-10T11:21:15.444Z",
      "nzd": "2024-09-10T11:21:15.444Z",
      "php": "2024-09-10T11:21:15.444Z",
      "pkr": "2024-09-10T11:21:15.444Z",
      "pln": "2024-09-10T11:21:15.444Z",
      "rub": "2024-09-10T11:21:15.444Z",
      "sar": "2024-09-10T11:21:15.444Z",
      "sats": "2024-12-05T07:03:15.394Z",
      "sek": "2024-09-10T11:21:15.444Z",
      "sgd": "2024-09-10T11:21:15.444Z",
      "thb": "2024-09-10T11:21:15.444Z",
      "try": "2024-09-10T11:21:15.444Z",
      "twd": "2024-09-10T11:21:15.444Z",
      "uah": "2024-09-10T11:21:15.444Z",
      "usd": "2024-09-10T11:21:15.444Z",
      "vef": "2024-09-10T11:21:15.444Z",
      "vnd": "2024-09-10T11:21:15.444Z",
      "xag": "2024-10-18T19:08:16.886Z",
      "xau": "2024-09-25T03:41:53.350Z",
      "xdr": "2024-09-10T11:21:15.444Z",
      "xlm": "2024-12-05T07:03:15.394Z",
      "xrp": "2024-12-17T11:30:45.797Z",
      "yfi": "2024-12-06T22:30:08.062Z",
      "zar": "2024-09-10T11:21:15.444Z"
    },
    "circulating_supply": 764575095.7022334,
    "current_price": {
      "aed": 0.00168343,
      "ars": 0.46806,
      "aud": 0.00072229,
      "bch": 8.48429e-07,
      "bdt": 0.054609,
      "bhd": 0.00017283,
      "bits": 0.00429543,
      "bmd": 0.00045833,
      "bnb": 6.37869e-07,
      "brl": 0.0028128,
      "btc": 4.295e-09,
      "cad": 0.00065436,
      "chf": 0.00041107,
      "clp": 0.45165,
      "cny": 0.00333864,
      "czk": 0.01094848,
      "dkk": 0.0032582,
      "dot": 5.163e-05,
      "eos": 0.00042775,
      "eth": 1.14678e-07,
      "eur": 0.00043682,
      "gbp": 0.00036094,
      "gel": 0.00128675,
      "hkd": 0.00356091,
      "huf": 0.178962,
      "idr": 7.4,
      "ils": 0.00165247,
      "inr": 0.03891555,
      "jpy": 0.07054,
      "krw": 0.659199,
      "kwd": 0.00014099,
      "link": 1.619e-05,
      "lkr": 0.132866,
      "ltc": 3.86e-06,
      "mmk": 0.961571,
      "mxn": 0.00921638,
      "myr": 0.00204712,
      "ngn": 0.711489,
      "nok": 0.00513737,
      "nzd": 0.00079543,
      "php": 0.02703765,
      "pkr": 0.127087,
      "pln": 0.00186165,
      "rub": 0.04709337,
      "sar": 0.001722,
      "sats": 0.429543,
      "sek": 0.00500911,
      "sgd": 0.00061901,
      "thb": 0.01569038,
      "try": 0.01603669,
      "twd": 0.01490344,
      "uah": 0.01909063,
      "usd": 0.00045833,
      "vef": 4.589e-05,
      "vnd": 11.66,
      "xag": 1.512e-05,
      "xau": 1.73518e-07,
      "xdr": 0.00034858,
      "xlm": 0.00099782,
      "xrp": 0.00017152,
      "yfi": 4.3298e-08,
      "zar": 0.00828179
    },
    "fdv_to_tvl_ratio": null,
    "fully_diluted_valuation": {
      "aed": 1286221,
      "ars": 357627818,
      "aud": 551937,
      "bch": 649.387,
      "bdt": 41723676,
      "bhd": 132051,
      "bits": 3284903,
      "bmd": 350185,
      "bnb": 488.217,
      "brl": 2150624,
      "btc": 3.284903,
      "cad": 500050,
      "chf": 314116,
      "clp": 345138516,
      "cny": 2550885,
      "czk": 8365181,
      "dkk": 2489405,
      "dot": 39538,
      "eos": 327544,
      "eth": 87.842,
      "eur": 333758,
      "gbp": 275756,
      "gel": 983143,
      "hkd": 2720645,
      "huf": 136729316,
      "idr": 5656259275,
      "ils": 1263447,
      "inr": 29734219,
      "jpy": 53897449,
      "krw": 503619216,
      "kwd": 107721,
      "link": 12391,
      "lkr": 101515830,
      "ltc": 2953,
      "mmk": 734687453,
      "mxn": 7040358,
      "myr": 1564100,
      "ngn": 542345017,
      "nok": 3925847,
      "nzd": 607983,
      "php": 20658094,
      "pkr": 97100588,
      "pln": 1422571,
      "rub": 35920374,
      "sar": 1315689,
      "sats": 328490296,
      "sek": 3826626,
      "sgd": 472959,
      "thb": 11988923,
      "try": 12252507,
      "twd": 11387481,
      "uah": 14586179,
      "usd": 350185,
      "vef": 35064,
      "vnd": 8906019838,
      "xag": 11548.1,
      "xau": 132.48,
      "xdr": 266331,
      "xlm": 762353,
      "xrp": 131283,
      "yfi": 33.136433,
      "zar": 6328446
    },
    "high_24h": {
      "aed": 0.00185273,
      "ars": 0.515148,
      "aud": 0.00079195,
      "bch": 9.42461e-07,
      "bdt": 0.060187,
      "bhd": 0.00019021,
      "bits": 0.00473802,
      "bmd": 0.00050442,
      "bnb": 7.00683e-07,
      "brl": 0.00310164,
      "btc": 4.738e-09,
      "cad": 0.00071855,
      "chf": 0.00045076,
      "clp": 0.496387,
      "cny": 0.0036732,
      "czk": 0.01200301,
      "dkk": 0.00357544,
      "dot": 5.782e-05,
      "eos": 0.00048844,
      "eth": 1.26288e-07,
      "eur": 0.00047934,
      "gbp": 0.00039738,
      "gel": 0.00141743,
      "hkd": 0.00392086,
      "huf": 0.195909,
      "idr": 8.09,
      "ils": 0.00181008,
      "inr": 0.04281807,
      "jpy": 0.077668,
      "krw": 0.723978,
      "kwd": 0.00015521,
      "link": 1.762e-05,
      "lkr": 0.146446,
      "ltc": 4.3e-06,
      "mmk": 1.058,
      "mxn": 0.0101463,
      "myr": 0.00224266,
      "ngn": 0.78147,
      "nok": 0.00562214,
      "nzd": 0.00087276,
      "php": 0.02963713,
      "pkr": 0.140077,
      "pln": 0.00203986,
      "rub": 0.052258,
      "sar": 0.00189515,
      "sats": 0.473802,
      "sek": 0.00548921,
      "sgd": 0.0006809,
      "thb": 0.01719491,
      "try": 0.01763853,
      "twd": 0.01639355,
      "uah": 0.02104076,
      "usd": 0.00050442,
      "vef": 5.051e-05,
      "vnd": 12.81,
      "xag": 1.653e-05,
      "xau": 1.89905e-07,
      "xdr": 0.00038419,
      "xlm": 0.00121198,
      "xrp": 0.00020364,
      "yfi": 4.714e-08,
      "zar": 0.00900406
    },
    "last_updated": "2024-12-17T12:19:35.474Z",
    "low_24h": {
      "aed": 0.00165998,
      "ars": 0.461091,
      "aud": 0.00071095,
      "bch": 8.32585e-07,
      "bdt": 0.05397,
      "bhd": 0.00017042,
      "bits": 0.00427587,
      "bmd": 0.00045194,
      "bnb": 6.31887e-07,
      "brl": 0.00273233,
      "btc": 4.276e-09,
      "cad": 0.00064395,
      "chf": 0.00040377,
      "clp": 0.444073,
      "cny": 0.00329172,
      "czk": 0.01077556,
      "dkk": 0.00321046,
      "dot": 5.029e-05,
      "eos": 0.00042758,
      "eth": 1.13002e-07,
      "eur": 0.00043041,
      "gbp": 0.00035701,
      "gel": 0.00126996,
      "hkd": 0.0035143,
      "huf": 0.176035,
      "idr": 7.23,
      "ils": 0.00162529,
      "inr": 0.03836062,
      "jpy": 0.06962,
      "krw": 0.649133,
      "kwd": 0.00013907,
      "link": 1.497e-05,
      "lkr": 0.13132,
      "ltc": 3.75e-06,
      "mmk": 0.948174,
      "mxn": 0.00911523,
      "myr": 0.00201227,
      "ngn": 0.701432,
      "nok": 0.00504607,
      "nzd": 0.00078316,
      "php": 0.02656672,
      "pkr": 0.125609,
      "pln": 0.00183493,
      "rub": 0.04693282,
      "sar": 0.00169785,
      "sats": 0.427587,
      "sek": 0.00493436,
      "sgd": 0.0006101,
      "thb": 0.01539223,
      "try": 0.01579993,
      "twd": 0.01467636,
      "uah": 0.01886751,
      "usd": 0.00045194,
      "vef": 4.525e-05,
      "vnd": 11.48,
      "xag": 1.473e-05,
      "xau": 1.6988e-07,
      "xdr": 0.00034451,
      "xlm": 0.00098854,
      "xrp": 0.00017122,
      "yfi": 4.1475e-08,
      "zar": 0.00807502
    },
    "market_cap": {
      "aed": 1286221,
      "ars": 357627818,
      "aud": 551937,
      "bch": 649.387,
      "bdt": 41723676,
      "bhd": 132051,
      "bits": 3284903,
      "bmd": 350185,
      "bnb": 488.217,
      "brl": 2150624,
      "btc": 3.284903,
      "cad": 500050,
      "chf": 314116,
      "clp": 345138516,
      "cny": 2550885,
      "czk": 8365181,
      "dkk": 2489405,
      "dot": 39538,
      "eos": 327544,
      "eth": 87.842,
      "eur": 333758,
      "gbp": 275756,
      "gel": 983143,
      "hkd": 2720645,
      "huf": 136729316,
      "idr": 5656259275,
      "ils": 1263447,
      "inr": 29734219,
      "jpy": 53897449,
      "krw": 503619216,
      "kwd": 107721,
      "link": 12391,
      "lkr": 101515830,
      "ltc": 2953,
      "mmk": 734687453,
      "mxn": 7040358,
      "myr": 1564100,
      "ngn": 542345017,
      "nok": 3925847,
      "nzd": 607983,
      "php": 20658094,
      "pkr": 97100588,
      "pln": 1422571,
      "rub": 35920374,
      "sar": 1315689,
      "sats": 328490296,
      "sek": 3826626,
      "sgd": 472959,
      "thb": 11988923,
      "try": 12252507,
      "twd": 11387481,
      "uah": 14586179,
      "usd": 350185,
      "vef": 35064,
      "vnd": 8906019838,
      "xag": 11548.1,
      "xau": 132.48,
      "xdr": 266331,
      "xlm": 762353,
      "xrp": 131283,
      "yfi": 33.136433,
      "zar": 6328446
    },
    "market_cap_change_24h": 1941.55,
    "market_cap_change_24h_in_currency": {
      "aed": 7134.77,
      "ars": 3121366,
      "aud": 3949.9,
      "bch": -13.11254412440519,
      "bdt": 226348,
      "bhd": 736.67,
      "bits": -65043.90341335535,
      "bmd": 1941.55,
      "bnb": -4.838651291705219,
      "brl": 35744,
      "btc": -0.06504390341335675,
      "cad": 4000.37,
      "chf": 3271.4,
      "clp": 2380221,
      "cny": 14212.69,
      "czk": 58503,
      "dkk": 14130.22,
      "dot": -624.3064554429511,
      "eos": -12862.977493411629,
      "eth": -1.0552451341723952,
      "eur": 1897.84,
      "gbp": 439.59,
      "gel": 4580.3,
      "hkd": 13072.45,
      "huf": 1137275,
      "idr": 76762358,
      "ils": 10342.23,
      "inr": 164281,
      "jpy": 336786,
      "krw": 3384630,
      "kwd": 560.68,
      "link": 666.037,
      "lkr": 745589,
      "ltc": -47.3147370126444,
      "mmk": 4073377,
      "mxn": 28418,
      "myr": 13547.35,
      "ngn": 3348238,
      "nok": 30902,
      "nzd": 4224.77,
      "php": 193240,
      "pkr": 550267,
      "pln": 7934.62,
      "rub": -331566.0680409521,
      "sar": 7386.6,
      "sats": -6504390.341335654,
      "sek": 11863.45,
      "sgd": 2931.85,
      "thb": 124279,
      "try": 76604,
      "twd": 77938,
      "uah": 118025,
      "usd": 1941.55,
      "vef": 194.41,
      "vnd": 61748718,
      "xag": 195.56,
      "xau": 1.77,
      "xdr": 2810.41,
      "xlm": -88046.10717277043,
      "xrp": -16304.487291237252,
      "yfi": 0.3588352,
      "zar": 93397
    },
    "market_cap_change_percentage_24h": 0.55753,
    "market_cap_change_percentage_24h_in_currency": {
      "aed": 0.5578,
      "ars": 0.88048,
      "aud": 0.7208,
      "bch": -1.97925,
      "bdt": 0.54545,
      "bhd": 0.56099,
      "bits": -1.94164,
      "bmd": 0.55753,
      "bnb": -0.98136,
      "brl": 1.6901,
      "btc": -1.94164,
      "cad": 0.80644,
      "chf": 1.05243,
      "clp": 0.69443,
      "cny": 0.56029,
      "czk": 0.70429,
      "dkk": 0.57085,
      "dot": -1.55447,
      "eos": -3.77871,
      "eth": -1.18704,
      "eur": 0.57188,
      "gbp": 0.15967,
      "gel": 0.46806,
      "hkd": 0.48281,
      "huf": 0.83875,
      "idr": 1.37579,
      "ils": 0.82533,
      "inr": 0.55557,
      "jpy": 0.62879,
      "krw": 0.67661,
      "kwd": 0.52322,
      "link": 5.6806,
      "lkr": 0.73989,
      "ltc": -1.57686,
      "mmk": 0.55753,
      "mxn": 0.40529,
      "myr": 0.87371,
      "ngn": 0.6212,
      "nok": 0.79338,
      "nzd": 0.69975,
      "php": 0.94425,
      "pkr": 0.56993,
      "pln": 0.56089,
      "rub": -0.91462,
      "sar": 0.56459,
      "sats": -1.94164,
      "sek": 0.31099,
      "sgd": 0.62376,
      "thb": 1.04748,
      "try": 0.62914,
      "twd": 0.68913,
      "uah": 0.81576,
      "usd": 0.55753,
      "vef": 0.55753,
      "vnd": 0.69818,
      "xag": 1.72263,
      "xau": 1.3505,
      "xdr": 1.06648,
      "xlm": -10.35351,
      "xrp": -11.04733,
      "yfi": 1.09476,
      "zar": 1.49794
    },
    "market_cap_fdv_ratio": 1,
    "market_cap_rank": 5005,
    "max_supply": 1000000000,
    "max_supply_infinite": false,
    "mcap_to_tvl_ratio": null,
    "price_change_24h": 2.22e-06,
    "price_change_24h_in_currency": {
      "aed": 8.14e-06,
      "ars": 0.0037409,
      "aud": 4.8e-06,
      "bch": -1.8366834351e-08,
      "bdt": 0.00014035,
      "bhd": 8.41713e-07,
      "bits": -9.2113803844747e-05,
      "bmd": 2.22e-06,
      "bnb": -8.356876983e-09,
      "brl": 3.632e-05,
      "btc": -9.2113804e-11,
      "cad": 4.6e-06,
      "chf": 3.91e-06,
      "clp": 0.00283178,
      "cny": 1.628e-05,
      "czk": 7.347e-05,
      "dkk": 1.721e-05,
      "dot": -1.021794499859e-06,
      "eos": -1.8338157169002e-05,
      "eth": -1.753570859e-09,
      "eur": 2.29e-06,
      "gbp": 3.97651e-07,
      "gel": 5.08e-06,
      "hkd": 1.457e-05,
      "huf": 0.00143056,
      "idr": 0.089205,
      "ils": 1.051e-05,
      "inr": 0.00018857,
      "jpy": 0.00035061,
      "krw": 0.00402619,
      "kwd": 6.33901e-07,
      "link": 7.75893e-07,
      "lkr": 0.00033398,
      "ltc": -7.1100882146e-08,
      "mmk": 0.00465,
      "mxn": 2.848e-05,
      "myr": 1.629e-05,
      "ngn": 0.0035866,
      "nok": 4.067e-05,
      "nzd": 4.99e-06,
      "php": 0.00023246,
      "pkr": 0.00031935,
      "pln": 9.49e-06,
      "rub": -0.000390278618626866,
      "sar": 8.45e-06,
      "sats": -0.00921138038447472,
      "sek": 1.866e-05,
      "sgd": 3.44e-06,
      "thb": 0.00014931,
      "try": 8.931e-05,
      "twd": 9.018e-05,
      "uah": 4.906e-05,
      "usd": 2.22e-06,
      "vef": 2.21928e-07,
      "vnd": 0.07257,
      "xag": 2.47766e-07,
      "xau": 2.244e-09,
      "xdr": 8.90668e-07,
      "xlm": -0.000116418746740167,
      "xrp": -2.1456738307067e-05,
      "yfi": 3.18938e-10,
      "zar": 0.00011832
    },
    "price_change_percentage_14d": -17.23518,
    "price_change_percentage_14d_in_currency": {
      "aed": -17.23586,
      "ars": -16.43932,
      "aud": -15.34393,
      "bch": -17.43194,
      "bdt": -17.75066,
      "bhd": -17.21015,
      "bits": -26.32925,
      "bmd": -17.23518,
      "bnb": -25.03104,
      "brl": -16.17527,
      "btc": -26.32925,
      "cad": -15.83179,
      "chf": -16.08248,
      "clp": -16.48087,
      "cny": -17.25449,
      "czk": -17.52212,
      "dkk": -16.99268,
      "dot": -6.40462,
      "eos": -9.01766,
      "eth": -25.15058,
      "eur": -16.99481,
      "gbp": -17.46136,
      "gel": -18.32611,
      "hkd": -17.38787,
      "huf": -17.87429,
      "idr": -16.15307,
      "ils": -17.9279,
      "inr": -17.00134,
      "jpy": -14.9284,
      "krw": -15.14656,
      "kwd": -17.17056,
      "link": -27.99152,
      "lkr": -17.73824,
      "ltc": -6.83025,
      "mmk": -17.23518,
      "mxn": -18.26381,
      "myr": -17.31664,
      "ngn": -22.62291,
      "nok": -16.14305,
      "nzd": -15.36324,
      "php": -16.68793,
      "pkr": -17.68943,
      "pln": -17.63825,
      "rub": -19.64087,
      "sar": -17.23459,
      "sats": -26.32925,
      "sek": -17.79663,
      "sgd": -16.86617,
      "thb": -17.68602,
      "try": -16.66532,
      "twd": -17.27792,
      "uah": -17.622,
      "usd": -17.23518,
      "vef": -17.23518,
      "vnd": -17.14327,
      "xag": -15.62322,
      "xau": -17.15641,
      "xdr": -17.56609,
      "xlm": -0.22857,
      "xrp": -12.31698,
      "yfi": -26.77353,
      "zar": -17.29834
    },
    "price_change_percentage_1h_in_currency": {
      "aed": -1.35518,
      "ars": -1.35643,
      "aud": -1.42722,
      "bch": -0.96512,
      "bdt": -1.35491,
      "bhd": -1.34575,
      "bits": -0.90761,
      "bmd": -1.35491,
      "bnb": -1.10827,
      "brl": -2.10304,
      "btc": -0.90761,
      "cad": -1.36804,
      "chf": -1.30737,
      "clp": -1.31485,
      "cny": -1.36303,
      "czk": -1.41848,
      "dkk": -1.41611,
      "dot": -0.97128,
      "eos": -0.40615,
      "eth": -0.94722,
      "eur": -1.41863,
      "gbp": -1.38384,
      "gel": -1.35484,
      "hkd": -1.34767,
      "huf": -1.39723,
      "idr": -1.28479,
      "ils": -1.21751,
      "inr": -1.35905,
      "jpy": -1.22095,
      "krw": -1.31971,
      "kwd": -1.361,
      "link": -0.97016,
      "lkr": -1.35491,
      "ltc": -1.20101,
      "mmk": -1.35491,
      "mxn": -1.39841,
      "myr": -1.35491,
      "ngn": -1.12434,
      "nok": -1.39385,
      "nzd": -1.40195,
      "php": -1.34906,
      "pkr": -1.35491,
      "pln": -1.4202,
      "rub": -1.23525,
      "sar": -1.35651,
      "sats": -0.90761,
      "sek": -1.37223,
      "sgd": -1.37937,
      "thb": -1.37364,
      "try": -1.3572,
      "twd": -1.31242,
      "uah": -1.35491,
      "usd": -1.35491,
      "vef": -1.35491,
      "vnd": -1.35491,
      "xag": -1.56525,
      "xau": -1.44602,
      "xdr": -1.35491,
      "xlm": 0.93831,
      "xrp": -0.12493,
      "yfi": -1.27429,
      "zar": -1.32332
    },
    "price_change_percentage_1y": -79.6641,
    "price_change_percentage_1y_in_currency": {
      "aed": -79.66252,
      "ars": -73.7563,
      "aud": -78.53425,
      "bch": -91.37641,
      "bdt": -78.0908,
      "bhd": -79.76797,
      "bits": -92.01145,
      "bmd": -79.6641,
      "bnb": -93.16611,
      "brl": -74.74929,
      "btc": -92.01145,
      "cad": -78.33067,
      "chf": -79.05677,
      "clp": -76.97479,
      "cny": -79.07848,
      "czk": -78.38125,
      "dkk": -78.87054,
      "dot": -83.94857,
      "eos": -84.369,
      "eth": -88.73653,
      "eur": -78.85769,
      "gbp": -79.67862,
      "gel": -78.77582,
      "hkd": -79.76295,
      "huf": -77.32573,
      "idr": -78.86374,
      "ils": -80.11631,
      "inr": -79.20716,
      "jpy": -77.97668,
      "krw": -77.47852,
      "kwd": -79.74915,
      "link": -89.78916,
      "lkr": -82.06979,
      "ltc": -87.59761,
      "mmk": -79.79286,
      "mxn": -76.2285,
      "myr": -80.56066,
      "ngn": -60.23112,
      "nok": -78.20803,
      "nzd": -78.09356,
      "php": -78.52235,
      "pkr": -79.95537,
      "pln": -79.11859,
      "rub": -76.94954,
      "sar": -79.63249,
      "sats": -92.01145,
      "sek": -78.22054,
      "sgd": -79.40965,
      "thb": -80.02743,
      "try": -75.44941,
      "twd": -78.9157,
      "uah": -77.25695,
      "usd": -79.6641,
      "vef": -79.6641,
      "vnd": -78.69437,
      "xag": -83.99166,
      "xau": -84.4503,
      "xdr": -79.57507,
      "xlm": -94.47603,
      "xrp": -95.28673,
      "yfi": -83.77196,
      "zar": -80.10284
    },
    "price_change_percentage_200d": -71.14175,
    "price_change_percentage_200d_in_currency": {
      "aed": -71.14167,
      "ars": -67.04339,
      "aud": -69.75579,
      "bch": -75.12001,
      "bdt": -70.70092,
      "bhd": -71.12843,
      "bits": -81.50572,
      "bmd": -71.14175,
      "bnb": -76.07167,
      "brl": -65.92248,
      "btc": -81.50572,
      "cad": -69.79679,
      "chf": -71.39669,
      "clp": -69.01628,
      "cny": -70.40809,
      "czk": -69.73156,
      "dkk": -70.1556,
      "dot": -77.22818,
      "eos": -77.99742,
      "eth": -72.50928,
      "eur": -70.15616,
      "gbp": -71.1095,
      "gel": -70.96074,
      "hkd": -71.32154,
      "huf": -68.55354,
      "idr": -71.35002,
      "ils": -72.01201,
      "inr": -70.628,
      "jpy": -71.73915,
      "krw": -69.99393,
      "kwd": -71.07753,
      "link": -81.5984,
      "lkr": -72.18261,
      "ltc": -79.56033,
      "mmk": -71.15675,
      "mxn": -65.85867,
      "myr": -72.61624,
      "ngn": -66.43158,
      "nok": -69.16565,
      "nzd": -69.29366,
      "php": -70.88461,
      "pkr": -71.23517,
      "pln": -70.17223,
      "rub": -67.11594,
      "sar": -71.09354,
      "sats": -81.50572,
      "sek": -70.03305,
      "sgd": -71.15657,
      "thb": -73.14048,
      "try": -68.66473,
      "twd": -71.08733,
      "uah": -70.34883,
      "usd": -71.14175,
      "vef": -71.14175,
      "vnd": -71.1601,
      "xag": -70.23228,
      "xau": -74.40209,
      "xdr": -70.94412,
      "xlm": -93.3051,
      "xrp": -94.36389,
      "yfi": -80.70767,
      "zar": -72.11969
    },
    "price_change_percentage_24h": 0.48593,
    "price_change_percentage_24h_in_currency": {
      "aed": 0.4858,
      "ars": 0.80567,
      "aud": 0.66959,
      "bch": -2.11893,
      "bdt": 0.25767,
      "bhd": 0.4894,
      "bits": -2.09944,
      "bmd": 0.48593,
      "bnb": -1.29318,
      "brl": 1.30801,
      "btc": -2.09944,
      "cad": 0.70841,
      "chf": 0.95972,
      "clp": 0.63094,
      "cny": 0.49007,
      "czk": 0.67557,
      "dkk": 0.5309,
      "dot": -1.94072,
      "eos": -4.11085,
      "eth": -1.5061,
      "eur": 0.52686,
      "gbp": 0.11029,
      "gel": 0.39653,
      "hkd": 0.41097,
      "huf": 0.80581,
      "idr": 1.22062,
      "ils": 0.64035,
      "inr": 0.48692,
      "jpy": 0.49952,
      "krw": 0.61452,
      "kwd": 0.45165,
      "link": 5.03446,
      "lkr": 0.252,
      "ltc": -1.81075,
      "mmk": 0.48593,
      "mxn": 0.30999,
      "myr": 0.80189,
      "ngn": 0.50665,
      "nok": 0.79788,
      "nzd": 0.63165,
      "php": 0.86723,
      "pkr": 0.25192,
      "pln": 0.51241,
      "rub": -0.82192,
      "sar": 0.493,
      "sats": -2.09944,
      "sek": 0.37392,
      "sgd": 0.5586,
      "thb": 0.96074,
      "try": 0.56005,
      "twd": 0.60876,
      "uah": 0.25766,
      "usd": 0.48593,
      "vef": 0.48593,
      "vnd": 0.62648,
      "xag": 1.66632,
      "xau": 1.31014,
      "xdr": 0.25617,
      "xlm": -10.44828,
      "xrp": -11.11869,
      "yfi": 0.74208,
      "zar": 1.44936
    },
    "price_change_percentage_30d": -25.4472,
    "price_change_percentage_30d_in_currency": {
      "aed": -25.4475,
      "ars": -23.65222,
      "aud": -24.08961,
      "bch": -38.96594,
      "bdt": -25.89125,
      "bhd": -25.32303,
      "bits": -36.65254,
      "bmd": -25.4472,
      "bnb": -34.56315,
      "brl": -21.07263,
      "btc": -36.65254,
      "cad": -24.51914,
      "chf": -24.69465,
      "clp": -24.67046,
      "cny": -24.91221,
      "czk": -25.68985,
      "dkk": -25.12184,
      "dot": -53.32952,
      "eos": -55.86901,
      "eth": -41.8875,
      "eur": -25.07725,
      "gbp": -25.91736,
      "gel": -23.47094,
      "hkd": -25.60185,
      "huf": -24.82284,
      "idr": -24.31371,
      "ils": -28.34738,
      "inr": -25.06773,
      "jpy": -25.65381,
      "krw": -23.18567,
      "kwd": -25.3336,
      "link": -62.74334,
      "lkr": -26.24437,
      "ltc": -44.61857,
      "mmk": -25.4472,
      "mxn": -26.31354,
      "myr": -25.5139,
      "ngn": -30.5494,
      "nok": -24.64284,
      "nzd": -25.19799,
      "php": -25.13278,
      "pkr": -25.76895,
      "pln": -26.08208,
      "rub": -23.29896,
      "sar": -25.42745,
      "sats": -36.65254,
      "sek": -25.78335,
      "sgd": -25.06492,
      "thb": -26.65508,
      "try": -24.21128,
      "twd": -25.35491,
      "uah": -25.04605,
      "usd": -25.4472,
      "vef": -25.4472,
      "vnd": -25.32396,
      "xag": -25.61542,
      "xau": -27.66359,
      "xdr": -24.9576,
      "xlm": -68.52039,
      "xrp": -70.78493,
      "yfi": -55.95395,
      "zar": -21.79823
    },
    "price_change_percentage_60d": 1.56958,
    "price_change_percentage_60d_in_currency": {
      "aed": 1.56917,
      "ars": 5.76529,
      "aud": 7.44718,
      "bch": -31.00387,
      "bdt": 1.25805,
      "bhd": 1.6073,
      "bits": -35.42856,
      "bmd": 1.56958,
      "bnb": -15.79613,
      "brl": 10.25003,
      "btc": -35.42856,
      "cad": 5.14282,
      "chf": 5.19067,
      "clp": 5.92288,
      "cny": 4.14592,
      "czk": 4.32981,
      "dkk": 5.03264,
      "dot": -51.59121,
      "eos": -54.55341,
      "eth": -33.29457,
      "eur": 5.0183,
      "gbp": 4.34815,
      "gel": 4.83698,
      "hkd": 1.56178,
      "huf": 7.50881,
      "idr": 5.81168,
      "ils": -1.2304,
      "inr": 2.57632,
      "jpy": 4.21619,
      "krw": 6.4881,
      "kwd": 1.93409,
      "link": -59.19292,
      "lkr": 0.5512,
      "ltc": -38.54723,
      "mmk": 1.56958,
      "mxn": 3.61055,
      "myr": 5.39215,
      "ngn": -3.57637,
      "nok": 4.68864,
      "nzd": 7.09759,
      "php": 4.23409,
      "pkr": 1.44369,
      "pln": 3.85201,
      "rub": 8.29017,
      "sar": 1.60273,
      "sats": -35.42856,
      "sek": 5.44724,
      "sgd": 4.54495,
      "thb": 4.85526,
      "try": 3.63094,
      "twd": 2.98529,
      "uah": 2.5988,
      "usd": 1.56958,
      "vef": 1.56958,
      "vnd": 2.64155,
      "xag": 7.48675,
      "xau": 4.20929,
      "xdr": 3.36522,
      "xlm": -78.74508,
      "xrp": -79.17557,
      "yfi": -52.50168,
      "zar": 4.39917
    },
    "price_change_percentage_7d": -6.96805,
    "price_change_percentage_7d_in_currency": {
      "aed": -6.96843,
      "ars": -6.46618,
      "aud": -6.1895,
      "bch": -6.65803,
      "bdt": -7.38224,
      "bhd": -6.95621,
      "bits": -14.71254,
      "bmd": -6.96805,
      "bnb": -9.56652,
      "brl": -6.17459,
      "btc": -14.71254,
      "cad": -6.22737,
      "chf": -5.1618,
      "clp": -5.58453,
      "cny": -6.58075,
      "czk": -6.75377,
      "dkk": -6.60699,
      "dot": -9.41631,
      "eos": -8.76349,
      "eth": -12.64514,
      "eur": -6.61865,
      "gbp": -6.52186,
      "gel": -7.05082,
      "hkd": -7.05293,
      "huf": -6.94123,
      "idr": -5.3901,
      "ils": -6.13398,
      "inr": -6.91192,
      "jpy": -5.61882,
      "krw": -6.47258,
      "kwd": -6.9387,
      "link": -23.70846,
      "lkr": -7.25327,
      "ltc": -11.95474,
      "mmk": -6.96805,
      "mxn": -7.28844,
      "myr": -6.15917,
      "ngn": -8.29312,
      "nok": -6.24685,
      "nzd": -5.97454,
      "php": -5.37769,
      "pkr": -7.32863,
      "pln": -6.74411,
      "rub": -5.35077,
      "sar": -6.95799,
      "sats": -14.71254,
      "sek": -7.16852,
      "sgd": -6.28464,
      "thb": -5.61153,
      "try": -6.59074,
      "twd": -7.02238,
      "uah": -6.91753,
      "usd": -6.96805,
      "vef": -6.96805,
      "vnd": -6.71961,
      "xag": -2.20123,
      "xau": -5.79355,
      "xdr": -6.90795,
      "xlm": -16.06968,
      "xrp": -22.7104,
      "yfi": -1.44942,
      "zar": -5.84501
    },
    "roi": null,
    "total_supply": 764575095.7022334,
    "total_value_locked": null,
    "total_volume": {
      "aed": 207965,
      "ars": 57822467,
      "aud": 89230,
      "bch": 104.812,
      "bdt": 6746160,
      "bhd": 21351,
      "bits": 530642,
      "bmd": 56620,
      "bnb": 78.8,
      "brl": 347484,
      "btc": 0.530642,
      "cad": 80837,
      "chf": 50783,
      "clp": 55795216,
      "cny": 412444,
      "czk": 1352537,
      "dkk": 402507,
      "dot": 6378,
      "eos": 52843,
      "eth": 14.166875,
      "eur": 53963,
      "gbp": 44590,
      "gel": 158961,
      "hkd": 439902,
      "huf": 22108360,
      "idr": 913850402,
      "ils": 204140,
      "inr": 4807491,
      "jpy": 8714258,
      "krw": 81435085,
      "kwd": 17417.1,
      "link": 2000,
      "lkr": 16413750,
      "ltc": 476.294,
      "mmk": 118789120,
      "mxn": 1138560,
      "myr": 252894,
      "ngn": 87894890,
      "nok": 634652,
      "nzd": 98265,
      "php": 3340137,
      "pkr": 15699864,
      "pln": 229982,
      "rub": 5817750,
      "sar": 212729,
      "sats": 53064200,
      "sek": 618807,
      "sgd": 76471,
      "thb": 1938335,
      "try": 1981117,
      "twd": 1841118,
      "uah": 2358390,
      "usd": 56620,
      "vef": 5669.38,
      "vnd": 1439984111,
      "xag": 1867.48,
      "xau": 21.44,
      "xdr": 43062,
      "xlm": 123267,
      "xrp": 21189,
      "yfi": 5.348876,
      "zar": 1023104
    }
  },
  "name": "Pepe Token",
  "platforms": {
    "ethereum": "0xbe042e9d09cb588331ff911c2b46fd833a3e5bd6"
  },
  "preview_listing": false,
  "public_notice": null,
  "sentiment_votes_down_percentage": 0,
  "sentiment_votes_up_percentage": 100,
  "status_updates": [],
  "symbol": "pepe",
  "tickers": [
    {
      "base": "PEPECOMMUNITY",
      "bid_ask_spread_percentage": 0.414666,
      "coin_id": "pepe-token",
      "converted_last": {
        "btc": 4.29e-09,
        "eth": 1.14528e-07,
        "usd": 0.00045744
      },
      "converted_volume": {
        "btc": 0.52262264,
        "eth": 13.953477,
        "usd": 55732
      },
      "is_anomaly": false,
      "is_stale": false,
      "last": 0.0004576,
      "last_fetch_at": "2024-12-17T12:18:44+00:00",
      "last_traded_at": "2024-12-17T12:18:44+00:00",
      "market": {
        "has_trading_incentive": false,
        "identifier": "mxc",
        "name": "MEXC"
      },
      "target": "USDT",
      "target_coin_id": "tether",
      "timestamp": "2024-12-17T12:18:44+00:00",
      "token_info_url": null,
      "trade_url": "https://www.mexc.com/exchange/PEPECOMMUNITY_USDT",
      "trust_score": "yellow",
      "volume": 121834605.92
    },
    {
      "base": "0XBE042E9D09CB588331FF911C2B46FD833A3E5BD6",
      "bid_ask_spread_percentage": 0.610198,
      "coin_id": "pepe-token",
      "converted_last": {
        "btc": 4.687e-09,
        "eth": 1.25137e-07,
        "usd": 0.00050008
      },
      "converted_volume": {
        "btc": 0.0080408,
        "eth": 0.21467124,
        "usd": 857.88
      },
      "is_anomaly": false,
      "is_stale": false,
      "last": 1.249580523e-07,
      "last_fetch_at": "2024-12-17T12:20:06+00:00",
      "last_traded_at": "2024-12-17T06:23:27+00:00",
      "market": {
        "has_trading_incentive": false,
        "identifier": "uniswap_v3",
        "name": "Uniswap V3 (Ethereum)"
      },
      "target": "0XC02AAA39B223FE8D0A0E5C4F27EAD9083C756CC2",
      "target_coin_id": "weth",
      "timestamp": "2024-12-17T06:23:27+00:00",
      "token_info_url": null,
      "trade_url": "https://app.uniswap.org/explore/tokens/ethereum/0xbe042e9d09cb588331ff911c2b46fd833a3e5bd6",
      "trust_score": "red",
      "volume": 1691854.84568063
    },
    {
      "base": "0XBE042E9D09CB588331FF911C2B46FD833A3E5BD6",
      "bid_ask_spread_percentage": 0.626039,
      "coin_id": "pepe-token",
      "converted_last": {
        "btc": 4.908e-09,
        "eth": 1.31174e-07,
        "usd": 0.0005231
      },
      "converted_volume": {
        "btc": 0.00025148,
        "eth": 0.00672155,
        "usd": 26.8
      },
      "is_anomaly": false,
      "is_stale": true,
      "last": 1.307975841e-07,
      "last_fetch_at": "2024-12-17T12:16:36+00:00",
      "last_traded_at": "2024-12-17T02:33:37+00:00",
      "market": {
        "has_trading_incentive": false,
        "identifier": "uniswap_v2",
        "name": "Uniswap V2 (Ethereum)"
      },
      "target": "0XC02AAA39B223FE8D0A0E5C4F27EAD9083C756CC2",
      "target_coin_id": "weth",
      "timestamp": "2024-12-17T02:33:37+00:00",
      "token_info_url": "https://v2.info.uniswap.org/token/0xbe042e9d09cb588331ff911c2b46fd833a3e5bd6",
      "trade_url": "https://app.uniswap.org/explore/tokens/ethereum/0xbe042e9d09cb588331ff911c2b46fd833a3e5bd6",
      "trust_score": "red",
      "volume": 51312.5486584416
    }
  ],
  "watchlist_portfolio_users": 3849,
  "web_slug": "pepe-token"
}